scikit_traveltime-0.1.4.dist-info/licenses/LICENSE
traveltime/__init__.py
traveltime/traveltime.py
scikit_traveltime-0.1.4.dist-info/METADATA
scikit_traveltime-0.1.4.dist-info/WHEEL
scikit_traveltime-0.1.4.dist-info/top_level.txt
scikit_traveltime-0.1.4.dist-info/RECORD
