Metadata-Version: 2.4
Name: scikit-traveltime
Version: 0.1.4
Summary: Traveltime computation using scikit-fmm
Author-email: Thomas Mejer Hansen <thomas.mejer.hansen@gmail.com>
License: MIT
Project-URL: Homepage, https://github.com/cultpenguin/scikit-traveltime
Project-URL: Repository, https://github.com/cultpenguin/scikit-traveltime
Project-URL: Download, https://github.com/cultpenguin/scikit-traveltime/archive/master.zip
Keywords: traveltime,eikonal,fast-marching
Classifier: Development Status :: 3 - Alpha
Classifier: License :: OSI Approved :: MIT License
Classifier: Programming Language :: Python :: 2.7
Classifier: Programming Language :: Python :: 3.6
Requires-Python: >=2.7
License-File: LICENSE
Requires-Dist: numpy>=1.0.2
Requires-Dist: scipy>=1.0.0
Requires-Dist: scikit-fmm>=0.0.9
Dynamic: license-file
